guard_decorator/__init__.py
guard_decorator-0.1.1.dist-info/LICENCE
guard_decorator-0.1.1.dist-info/METADATA
guard_decorator-0.1.1.dist-info/WHEEL
guard_decorator-0.1.1.dist-info/top_level.txt
guard_decorator-0.1.1.dist-info/RECORD
