Metadata-Version: 2.1
Name: guard_decorator
Version: 0.1.1
Summary: A decorator to simplify error handling in Python.
Home-page: https://github.com/xilax79/guard_decorator
Author: xilax79
Author-email: xilax79@gmail.com
License: Apache 2.0
Classifier: Programming Language :: Python :: 3
Classifier: License :: OSI Approved :: Apache Software License
Classifier: Operating System :: OS Independent
Requires-Python: >=3.6
License-File: LICENCE
